{
  "appPageId" : "9c02c4ef-a8e6-4be2-bf1e-296dbcdf439d",
  "componentName" : "siteforce:sldsTwoCol48Layout",
  "id" : "81991e28-d791-456b-b918-9c4caed540fa",
  "label" : "Home",
  "regions" : [ {
    "id" : "660e1d61-6a92-4b41-a8d0-2f0cb7f09176",
    "regionName" : "header",
    "type" : "region"
  }, {
    "components" : [ {
      "componentAttributes" : {
        "buttonAlignment" : "center",
        "buttonBgColor" : "",
        "buttonBgHoverColor" : "",
        "buttonBorderColor" : "",
        "buttonMaxWidth" : 100,
        "buttonRadius" : 0,
        "buttonTextColor" : "",
        "buttonTextHoverColor" : "",
        "confirmationMessage" : "Got it!",
        "followUpPromptLabel" : "Can we close your question?",
        "isAskFollowPromptEnabled" : true,
        "isIncludeArticlesEnabled" : false,
        "isIncludeDiscussionsEnabled" : true,
        "isInitialSatisfactionPromptEnabled" : true,
        "isPublisherDeflectionEnabled" : true,
        "label" : "Ask a Question",
        "maxSuggestions" : 5,
        "satisfactionPromptLabel" : "Did we help to answer your question?",
        "showDetails" : false,
        "showTopics" : true,
        "uneditableTopics" : false
      },
      "componentName" : "forceCommunity:askCommunity",
      "id" : "48ed9261-3e40-4c3f-9bbc-9c93056b25a2",
      "renderPriority" : "NEUTRAL",
      "renditionMap" : { },
      "type" : "component"
    } ],
    "id" : "90dc156f-6c09-4fcc-a581-0db12e553608",
    "regionName" : "featured",
    "type" : "region"
  }, {
    "components" : [ {
      "componentAttributes" : {
        "bannerBackgroundColor" : "rgb(1, 139, 255)",
        "bannerPosition" : "top",
        "bannerSizePercent" : 35,
        "borderRadius" : 0,
        "boxShadow" : true,
        "haveBanner" : true,
        "iconBackgroundColor" : "rgb(255,255,255)",
        "iconSize" : "medium",
        "noImageColor" : "rgba(229, 229, 229, 0)",
        "overlay" : "rgb(255, 255, 255)",
        "templateType" : "icon",
        "tileMenuEditor" : "Home_Tile_Menu",
        "titleColor" : "rgb(0, 0, 0)",
        "titleFontSize" : "large",
        "titleHorizontalAlign" : "center"
      },
      "componentName" : "community_navigation:tileMenu",
      "id" : "7432c460-86e7-473c-9985-91a81ad8b8ec",
      "renderPriority" : "NEUTRAL",
      "renditionMap" : { },
      "type" : "component"
    } ],
    "id" : "831beb16-86da-44f1-804b-8245c0cf5f4c",
    "regionName" : "content",
    "type" : "region"
  }, {
    "components" : [ {
      "componentAttributes" : {
        "flowArguments" : "",
        "flowLayout" : "oneColumn",
        "flowName" : "X6_FF_PROJECT_SF_Display_Project_Related_Contacts_to_PS_Customer_in_Community"
      },
      "componentName" : "forceCommunity:flowCommunity",
      "id" : "30829ffc-3e49-4ada-b154-6e323d787751",
      "renderPriority" : "NEUTRAL",
      "renditionMap" : { },
      "type" : "component"
    }, {
      "componentAttributes" : {
        "richTextValue" : "<p><a href=\"https://neo4j.force.com/Neo4jCustomerServicePortal/s/ps-customer-onboarding-portal-guidance\" rel=\"noopener noreferrer\" target=\"_blank\"><img class=\"sfdcCbImage\" src=\"{!contentAsset.Community_Button_v1.1}\"></a></p>"
      },
      "componentName" : "forceCommunity:richTextInline",
      "id" : "235e90f5-06aa-4275-a4c1-580bd828d745",
      "renderPriority" : "NEUTRAL",
      "renditionMap" : { },
      "type" : "component"
    } ],
    "id" : "e3a3cef3-ebc5-4797-84d8-97efb01ff12f",
    "regionName" : "sidebar",
    "type" : "region"
  }, {
    "id" : "938d98eb-e550-43df-a437-a7735f862840",
    "regionName" : "footer",
    "type" : "region"
  }, {
    "components" : [ {
      "componentAttributes" : {
        "customHeadTags" : "",
        "description" : "",
        "title" : "Home"
      },
      "componentName" : "forceCommunity:seoAssistant",
      "id" : "ef886dce-a674-4ace-91c6-4a225fc447cf",
      "renditionMap" : { },
      "type" : "component"
    } ],
    "id" : "0fc91462-f7fe-4323-a042-fab1d5f5f9b3",
    "regionName" : "sfdcHiddenRegion",
    "type" : "region"
  }, {
    "components" : [ {
      "componentAttributes" : {
        "buttonAlignment" : "right",
        "buttonBgColor" : "",
        "buttonBgHoverColor" : "",
        "buttonBorderColor" : "",
        "buttonMaxWidth" : 100,
        "buttonRadius" : 0,
        "buttonTextColor" : "",
        "buttonTextHoverColor" : "",
        "confirmationMessage" : "Got it!",
        "followUpPromptLabel" : "Can we close your question?",
        "isAskFollowPromptEnabled" : true,
        "isIncludeArticlesEnabled" : false,
        "isIncludeDiscussionsEnabled" : true,
        "isInitialSatisfactionPromptEnabled" : true,
        "isPublisherDeflectionEnabled" : true,
        "label" : "Ask a Question",
        "maxSuggestions" : 5,
        "satisfactionPromptLabel" : "Did we help to answer your question?",
        "showDetails" : true,
        "showTopics" : false,
        "uneditableTopics" : false
      },
      "componentName" : "forceCommunity:askCommunity",
      "id" : "199e1c76-4b79-4286-b7bc-3cdcdcc8f93e",
      "renderPriority" : "NEUTRAL",
      "renditionMap" : { },
      "type" : "component"
    } ],
    "id" : "c74360ce-41b1-4561-9a01-948963977474",
    "regionName" : "sidebarAlt",
    "type" : "region"
  } ],
  "themeLayoutType" : "Home",
  "type" : "view",
  "viewType" : "home"
}